<?xml version="1.0" encoding="utf-8" ?>
<dwsync>
<file name=".csscomb.json" server="componto.pt//dev/warmrental/" local="130626229099731585" remote="130496738400000000" Dst="1" />
<file name=".csslintrc" server="componto.pt//dev/warmrental/" local="130626229099711513" remote="130496738400000000" Dst="1" />
<file name="alerts.less" server="componto.pt//dev/warmrental/" local="130626229101161744" remote="130496738400000000" Dst="1" />
<file name="badges.less" server="componto.pt//dev/warmrental/" local="130626229101151729" remote="130496738400000000" Dst="1" />
<file name="breadcrumbs.less" server="componto.pt//dev/warmrental/" local="130626229102571927" remote="130496738400000000" Dst="1" />
<file name="bootstrap.less" server="componto.pt//dev/warmrental/" local="130626229101171712" remote="130496738400000000" Dst="1" />
<file name="button-groups.less" server="componto.pt//dev/warmrental/" local="130626229102582185" remote="130496738400000000" Dst="1" />
<file name="carousel.less" server="componto.pt//dev/warmrental/" local="130626229103902085" remote="130496738400000000" Dst="1" />
<file name="buttons.less" server="componto.pt//dev/warmrental/" local="130626229102571927" remote="130496738400000000" Dst="1" />
<file name="close.less" server="componto.pt//dev/warmrental/" local="130626229103822706" remote="130496738400000000" Dst="1" />
<file name="code.less" server="componto.pt//dev/warmrental/" local="130626229103832057" remote="130496738400000000" Dst="1" />
<file name="component-animations.less" server="componto.pt//dev/warmrental/" local="130626229105062717" remote="130496738400000000" Dst="1" />
<file name="dropdowns.less" server="componto.pt//dev/warmrental/" local="130626229105062717" remote="130496738400000000" Dst="1" />
<file name="forms.less" server="componto.pt//dev/warmrental/" local="130626229105082214" remote="130496738400000000" Dst="1" />
<file name="glyphicons.less" server="componto.pt//dev/warmrental/" local="130626229106472350" remote="130496738400000000" Dst="1" />
<file name="grid.less" server="componto.pt//dev/warmrental/" local="130626229106482365" remote="130496738400000000" Dst="1" />
<file name="input-groups.less" server="componto.pt//dev/warmrental/" local="130626229106492794" remote="130496738400000000" Dst="1" />
<file name="jumbotron.less" server="componto.pt//dev/warmrental/" local="130626229107832523" remote="130496738400000000" Dst="1" />
<file name="labels.less" server="componto.pt//dev/warmrental/" local="130626229107832523" remote="130496738400000000" Dst="1" />
<file name="media.less" server="componto.pt//dev/warmrental/" local="130626229109122728" remote="130496738400000000" Dst="1" />
<file name="list-group.less" server="componto.pt//dev/warmrental/" local="130626229107822816" remote="130496738400000000" Dst="1" />
<file name="mixins.less" server="componto.pt//dev/warmrental/" local="130626229122084381" remote="130496738400000000" Dst="1" />
<file name="modals.less" server="componto.pt//dev/warmrental/" local="130626229122074650" remote="130496738400000000" Dst="1" />
<file name="navbar.less" server="componto.pt//dev/warmrental/" local="130626229122094733" remote="130496738400000000" Dst="1" />
<file name="navs.less" server="componto.pt//dev/warmrental/" local="130626229123354562" remote="130496738400000000" Dst="1" />
<file name="normalize.less" server="componto.pt//dev/warmrental/" local="130626229123364565" remote="130496738400000000" Dst="1" />
<file name="pager.less" server="componto.pt//dev/warmrental/" local="130626229123354562" remote="130496738400000000" Dst="1" />
<file name="pagination.less" server="componto.pt//dev/warmrental/" local="130626229124614734" remote="130496738400000000" Dst="1" />
<file name="panels.less" server="componto.pt//dev/warmrental/" local="130626229124605044" remote="130496738400000000" Dst="1" />
<file name="popovers.less" server="componto.pt//dev/warmrental/" local="130626229124605044" remote="130496738400000000" Dst="1" />
<file name="print.less" server="componto.pt//dev/warmrental/" local="130626229125844997" remote="130496738400000000" Dst="1" />
<file name="progress-bars.less" server="componto.pt//dev/warmrental/" local="130626229125874840" remote="130496738400000000" Dst="1" />
<file name="responsive-embed.less" server="componto.pt//dev/warmrental/" local="130626229125864968" remote="130496738400000000" Dst="1" />
<file name="responsive-utilities.less" server="componto.pt//dev/warmrental/" local="130626229127165027" remote="130496738400000000" Dst="1" />
<file name="scaffolding.less" server="componto.pt//dev/warmrental/" local="130626229127155024" remote="130496738400000000" Dst="1" />
<file name="tables.less" server="componto.pt//dev/warmrental/" local="130626229127185028" remote="130496738400000000" Dst="1" />
<file name="theme.less" server="componto.pt//dev/warmrental/" local="130626229158378962" remote="130496738400000000" Dst="1" />
<file name="thumbnails.less" server="componto.pt//dev/warmrental/" local="130626229158378962" remote="130496738400000000" Dst="1" />
<file name="tooltip.less" server="componto.pt//dev/warmrental/" local="130626229158398957" remote="130496738400000000" Dst="1" />
<file name="type.less" server="componto.pt//dev/warmrental/" local="130626229162199485" remote="130496738400000000" Dst="1" />
<file name="utilities.less" server="componto.pt//dev/warmrental/" local="130626229159639709" remote="130496738400000000" Dst="1" />
<file name="variables.less" server="componto.pt//dev/warmrental/" local="130626229162209488" remote="130496738400000000" Dst="1" />
<file name="wells.less" server="componto.pt//dev/warmrental/" local="130626229163439644" remote="130496738400000000" Dst="1" />
</dwsync>